securitytrailsapi/__init__.py
securitytrailsapi/api_handler.py
securitytrailsapi-0.0.1.dist-info/LICENSE
securitytrailsapi-0.0.1.dist-info/METADATA
securitytrailsapi-0.0.1.dist-info/WHEEL
securitytrailsapi-0.0.1.dist-info/top_level.txt
securitytrailsapi-0.0.1.dist-info/RECORD
