Metadata-Version: 2.1
Name: securitytrailsapi
Version: 0.0.1
Summary: A wrapper around the SecurityTrails API
Home-page: https://github.com/hangmansROP/securitytrailsapi
Author: Dan Duffy
Author-email: de4db1t@gmail.com
License: UNKNOWN
Platform: UNKNOWN
Classifier: Programming Language :: Python :: 3
Classifier: License :: OSI Approved :: GNU General Public License v3 (GPLv3)
Classifier: Operating System :: OS Independent
